d_py/__init__.py
d_py-0.0.2.dist-info/WHEEL
d_py-0.0.2.dist-info/METADATA
d_py-0.0.2.dist-info/RECORD
